plug_in_django/__init__.py
plug_in_django/manage.py
plug_in_django/plug_in_django/__init__.py
plug_in_django/plug_in_django/routing.py
plug_in_django/plug_in_django/settings.py
plug_in_django/plug_in_django/urls.py
plug_in_django/plug_in_django/wsgi.py
plug_in_django/static/basic.css
plug_in_django/templates/plug_in_django_basic.html
plug_in_django/templates/plug_in_django_index.html
plug_in_django/templatetags/__init__.py
plug_in_django/templatetags/installed_apps.py
plug_in_django/templatetags/public_dict.py
PlugInDjango-0.1.1566390774.dist-info/LICENSE.txt
PlugInDjango-0.1.1566390774.dist-info/METADATA
PlugInDjango-0.1.1566390774.dist-info/WHEEL
PlugInDjango-0.1.1566390774.dist-info/top_level.txt
PlugInDjango-0.1.1566390774.dist-info/RECORD
